lexisnexisapi/__init__.py
lexisnexisapi/credentials.py
lexisnexisapi/metabase.py
lexisnexisapi/webservices.py
lexisnexisapi-3.0.3.12.dist-info/LICENSE.txt
lexisnexisapi-3.0.3.12.dist-info/METADATA
lexisnexisapi-3.0.3.12.dist-info/WHEEL
lexisnexisapi-3.0.3.12.dist-info/top_level.txt
lexisnexisapi-3.0.3.12.dist-info/RECORD
