Metadata-Version: 2.1
Name: lexisnexisapi
Version: 3.0.3.12
Summary: a module to support lexisnexis api(s)
Home-page: https://pypi.org/project/lexisnexisapi/
Author: Robert Cuffney
Author-email: Robert Cuffney <robert.cuffney@lexisnexis.com>
License: MIT
Keywords: metabase webservices lexisnexis
License-File: LICENSE.txt
Requires-Dist: pandas
Requires-Dist: requests
Requires-Dist: xmltodict
